isignored/__init__.py
isignored-0.1.1.dist-info/METADATA
isignored-0.1.1.dist-info/WHEEL
isignored-0.1.1.dist-info/licenses/LICENSE
isignored-0.1.1.dist-info/RECORD
