Metadata-Version: 2.4
Name: isignored
Version: 0.1.1
Summary: Utility for checking whether a path is ignored by ignore files like .gitignore
Project-URL: Homepage, https://github.com/nielsrolf/isignored
Project-URL: Repository, https://github.com/nielsrolf/isignored
Project-URL: Issues, https://github.com/nielsrolf/isignored/issues
Author: Niels Warncke
License: MIT
License-File: LICENSE
Keywords: files,gitignore,ignore,patterns
Classifier: Development Status :: 4 - Beta
Classifier: Intended Audience :: Developers
Classifier: License :: OSI Approved :: MIT License
Classifier: Operating System :: OS Independent
Classifier: Programming Language :: Python :: 3
Classifier: Programming Language :: Python :: 3.9
Classifier: Programming Language :: Python :: 3.10
Classifier: Programming Language :: Python :: 3.11
Classifier: Programming Language :: Python :: 3.12
Classifier: Topic :: Software Development :: Libraries :: Python Modules
Classifier: Topic :: Utilities
Requires-Python: >=3.9
